gamegym/__init__.py
gamegym/errors.py
gamegym/game.py
gamegym/situation.py
gamegym/strategy.py
gamegym/utils.py
gamegym/algorithms/__init__.py
gamegym/algorithms/bestresponse.py
gamegym/algorithms/infosets.py
gamegym/algorithms/mccfr.py
gamegym/algorithms/stats.py
gamegym/contrib/__init__.py
gamegym/contrib/features.py
gamegym/contrib/gambit.py
gamegym/contrib/strategy_trace.py
gamegym/contrib/value_learning/__init__.py
gamegym/contrib/value_learning/expected_features.py
gamegym/contrib/value_learning/value_full_sgd.py
gamegym/contrib/value_learning/valuelp.py
gamegym/contrib/value_learning/valuesgd.py
gamegym/contrib/value_learning/valuestore.py
gamegym/games/__init__.py
gamegym/games/dicepoker.py
gamegym/games/goofspiel.py
gamegym/games/matrix.py
gamegym/games/onecardpoker.py
gamegym-0.2.0.dist-info/LICENCE
gamegym-0.2.0.dist-info/METADATA
gamegym-0.2.0.dist-info/WHEEL
gamegym-0.2.0.dist-info/top_level.txt
gamegym-0.2.0.dist-info/RECORD
