Metadata-Version: 2.1
Name: gamegym
Version: 0.2.0
Summary: Game theory framework, algorithms and game implementations
Home-page: https://github.com/gavento/gamegym
Author: Tomáš Gavenčiak
Author-email: gavento@gmail.com
License: UNKNOWN
Platform: UNKNOWN
Classifier: Programming Language :: Python :: 3
Classifier: License :: OSI Approved :: MIT License
Classifier: Operating System :: OS Independent
Requires-Dist: numpy (>=1.15)
Requires-Dist: attrs (>=18.0)
Requires-Dist: tqdm (>=4.28)
Provides-Extra: dev
Requires-Dist: codecov ; extra == 'dev'
Requires-Dist: coverage (>=4.0) ; extra == 'dev'
Requires-Dist: coveralls ; extra == 'dev'
Requires-Dist: flake8 (>=3.0) ; extra == 'dev'
Requires-Dist: pylint (>=2.0) ; extra == 'dev'
Requires-Dist: pytest-benchmark (>=3.0) ; extra == 'dev'
Requires-Dist: pytest (>=4.0) ; extra == 'dev'
Requires-Dist: tox-travis ; extra == 'dev'
Requires-Dist: tox ; extra == 'dev'
Requires-Dist: yapf ; extra == 'dev'
